fmap-0.1.dist-info/RECORD
fmap-0.1.dist-info/entry_points.txt
fmap-0.1.dist-info/metadata.json
fmap-0.1.dist-info/METADATA
fmap-0.1.dist-info/DESCRIPTION.rst
fmap-0.1.dist-info/top_level.txt
fmap-0.1.dist-info/WHEEL
fmap/_fmap.py
fmap/__init__.py
fmap/main.py
fmap/__main__.py
