Metadata-Version: 2.0
Name: fmap
Version: 0.1
Summary: A command-line utility for recursively applying a command to a filesystem tree
Home-page: https://github.com/mbodenhamer/fmap
Author: Matt Bodenhamer
Author-email: mbodenhamer@mbodenhamer.com
License: MIT
Keywords: fmap,recursive,apply,command,filesystem tree,find
Platform: UNKNOWN
Classifier: Development Status :: 4 - Beta
Classifier: Environment :: Console
Classifier: Intended Audience :: Developers
Classifier: Intended Audience :: System Administrators
Classifier: License :: OSI Approved :: MIT License
Classifier: Operating System :: OS Independent
Classifier: Programming Language :: Python
Classifier: Programming Language :: Python :: 2.7
Classifier: Programming Language :: Python :: 3.3
Classifier: Programming Language :: Python :: 3.4
Classifier: Programming Language :: Python :: 3.5
Classifier: Topic :: System :: Systems Administration
Classifier: Topic :: Utilities
Requires-Dist: six
